gym_eyesim/__init__.py
gym_eyesim/envs/__init__.py
gym_eyesim/envs/eyebot_env.py
gym_eyesim/utils/__init__.py
gym_eyesim/utils/coordinates.py
gym_eyesim/utils/geometry.py
gym_eyesim/utils/road.py
gym_eyesim-0.0.18.dist-info/METADATA
gym_eyesim-0.0.18.dist-info/WHEEL
gym_eyesim-0.0.18.dist-info/top_level.txt
gym_eyesim-0.0.18.dist-info/RECORD
