Metadata-Version: 2.1
Name: gym-eyesim
Version: 0.0.18
Summary: EyeSim Gym Env
Home-page: https://gitlab.com/felixwege/gym-eyesim
Author: Felix Wege
Author-email: felix.wege@tuhh.de
License: GPLv3
Platform: UNKNOWN
Requires-Dist: gym (>=0.15.4)
Requires-Dist: numpy (>=1.17.4)
Requires-Dist: opencv-python (>=4.1.2.30)
Requires-Dist: psutil (>=5.6.7)
Requires-Dist: scikit-learn (>=0.21.3)
Requires-Dist: scipy (>=1.3.3)
